jyboss/__init__.py
jyboss/ansible.py
jyboss/cli.py
jyboss/context.py
jyboss/exceptions.py
jyboss/logging.py
jyboss/command/__init__.py
jyboss/command/binding.py
jyboss/command/core.py
jyboss/command/datasources.py
jyboss/command/deployment.py
jyboss/command/ee.py
jyboss/command/extension.py
jyboss/command/infinispan.py
jyboss/command/interface.py
jyboss/command/jgroups.py
jyboss/command/keycloak.py
jyboss/command/modcluster.py
jyboss/command/module.py
jyboss/command/security.py
jyboss/command/undertow.py
jyboss/command/weld.py
jyboss-0.2.8.dist-info/LICENSE.txt
jyboss-0.2.8.dist-info/METADATA
jyboss-0.2.8.dist-info/WHEEL
jyboss-0.2.8.dist-info/top_level.txt
jyboss-0.2.8.dist-info/RECORD
