Metadata-Version: 2.1
Name: jyboss
Version: 0.2.8
Summary: Jython CLI for JBoss Application Server
Home-page: https://github.com/fareliner/jyboss-cli
Author: Niels Bertram
Author-email: nielsbne@gmail.com
License: Apache License 2.0
Keywords: jboss wildfly development cli
Platform: UNKNOWN
Classifier: Development Status :: 4 - Beta
Classifier: Intended Audience :: Developers
Classifier: Topic :: Software Development :: Build Tools
Classifier: Topic :: System :: Software Distribution
Classifier: Topic :: System :: Systems Administration
Classifier: License :: OSI Approved :: Apache Software License
Classifier: Natural Language :: English
Classifier: Programming Language :: Python :: 2
Classifier: Programming Language :: Python :: 2.7
Classifier: Programming Language :: Python :: 3
Classifier: Programming Language :: Python :: 3.3
Classifier: Programming Language :: Python :: 3.4
Classifier: Programming Language :: Python :: 3.5
Classifier: Programming Language :: Python :: Implementation :: Jython
Requires-Dist: simplejson
Requires-Dist: PyYAML
